modules/SR.py
modules/__init__.py
pySRM-0.1.2.dist-info/METADATA
pySRM-0.1.2.dist-info/WHEEL
pySRM-0.1.2.dist-info/top_level.txt
pySRM-0.1.2.dist-info/RECORD
