Metadata-Version: 2.1
Name: pySRM
Version: 0.1.2
Summary: a Python package for the segmented regression model
Home-page: https://github.com/ycc252/pySRM
Author: Yijing Yang
Author-email: yijing.Yang@rub.de
License: MIT
Platform: UNKNOWN
Classifier: Programming Language :: Python :: 3
Classifier: License :: OSI Approved :: MIT License
Classifier: Operating System :: OS Independent
Requires-Python: >=3.6
